rgwfuncs/__init__.py
rgwfuncs/df_lib.py
rgwfuncs/docs_lib.py
rgwfuncs/interactive_shell_lib.py
rgwfuncs/str_lib.py
rgwfuncs-0.0.117.dist-info/licenses/LICENSE
rgwfuncs-0.0.117.dist-info/METADATA
rgwfuncs-0.0.117.dist-info/WHEEL
rgwfuncs-0.0.117.dist-info/top_level.txt
rgwfuncs-0.0.117.dist-info/RECORD
