Metadata-Version: 2.4
Name: rgwfuncs
Version: 0.0.117
Summary: A functional programming paradigm for mathematical modelling and data science
Author-email: Ryan Gerard Wilson <ryangerardwilson@gmail.com>
Project-URL: Homepage, https://github.com/ryangerardwilson/rgwfuncs
Project-URL: Issues, https://github.com/ryangerardwilson/rgwfuncs
Classifier: Programming Language :: Python :: 3
Classifier: License :: OSI Approved :: MIT License
Classifier: Operating System :: OS Independent
Requires-Python: >=3.10
License-File: LICENSE
Requires-Dist: pandas
Requires-Dist: pymssql
Requires-Dist: mysql-connector-python
Requires-Dist: clickhouse-connect
Requires-Dist: google-cloud-bigquery
Requires-Dist: google-auth
Requires-Dist: xgboost
Requires-Dist: requests
Requires-Dist: slack-sdk
Requires-Dist: google-api-python-client
Requires-Dist: boto3
Requires-Dist: pyfiglet
Requires-Dist: snowflake-connector-python
Dynamic: license-file
